pytn/MainFiles.py
pytn/SupportFuncs.py
pytn/__init__.py
pytn/compiler.py
pytn-1.2.dist-info/LICENSE
pytn-1.2.dist-info/METADATA
pytn-1.2.dist-info/WHEEL
pytn-1.2.dist-info/top_level.txt
pytn-1.2.dist-info/RECORD
