Metadata-Version: 2.1
Name: pytn
Version: 1.2
Summary: Python text notation
Home-page: https://github.com/kshitij1235/filemod
Author: kshitij jathar
Author-email: kshitijjathar7@gmail.com
License: MIT
Project-URL: Bug Tracker, https://github.com/kshitij1235/filemod/issues
Keywords: file
Classifier: Intended Audience :: Education
Classifier: Operating System :: Microsoft :: Windows :: Windows 10
Classifier: License :: OSI Approved :: MIT License
Classifier: Programming Language :: Python :: 3.5
Classifier: Programming Language :: Python :: 3.6
Classifier: Programming Language :: Python :: 3.7
Classifier: Programming Language :: Python :: 3.8
License-File: LICENSE
Requires-Dist: filemod
